{
  "$schema": "http://json-schema.org/draft-04/schema#",
  "additionalProperties": false,
  "properties": {
    "repositoryID": {
      "description": "The ID of the Artifact Hub repository where the packages will be published to (optional, but it enables verified publisher)",
      "type": "string",
      "format": "uuid"
    },
    "owners": {
      "description": "Used to claim repository ownership",
      "type": "array",
      "items": {
        "type": "object",
        "additionalProperties": false,
        "properties": {
          "name": {
            "type": "string"
          },
          "email": {
            "type": "string",
            "format": "email"
          }
        }
      }
    },
    "ignore": {
      "description": "Packages that should not be indexed by Artifact Hub",
      "type": "array",
      "items": {
        "type": "object",
        "additionalProperties": false,
        "required": ["name"],
        "properties": {
          "name": {
            "description": "Exact match",
            "type": "string"
          },
          "version": {
            "description": "Regular expression (when omitted, all versions are ignored)",
            "type": "string"
          }
        }
      }
    }
  },
  "title": "Artifact Hub repository metadata file",
  "type": "object"
}
