{
  "$schema": "http://json-schema.org/draft-04/schema",
  "additionalProperties": {
    "$ref": "#/definitions/job"
  },
  "definitions": {
    "deployment": {
      "description": "A deployment project in Bamboo is a container for holding the software project you are deploying: releases that have been built and tested, and the environments to which releases are deployed",
      "properties": {
        "name": {
          "type": "string"
        },
        "source-plan": {
          "type": "string"
        }
      },
      "title": "Deployment projects",
      "type": "object"
    },
    "docker": {
      "anyOf": [
        {
          "type": "string"
        },
        {
          "properties": {
            "image": {
              "type": "string"
            },
            "use-default-volumes": {
              "default": false,
              "type": "boolean"
            },
            "volumes": {
              "default": {},
              "type": "object"
            }
          },
          "required": ["image"],
          "type": "object"
        }
      ],
      "description": "Builds and deployments are normally run on the Bamboo agent’s native operating system",
      "title": "Docker"
    },
    "events": {
      "enum": [
        "plan-failed",
        "plan-completed",
        "plan-status-changed",
        "plan-comment-added",
        "plan-responsibility-changed",
        "job-completed",
        "job-status-changed",
        "job-failed",
        "job-error",
        "job-first-failed",
        "job-hung",
        "job-queue-timeout",
        "job-queued-without-capable-agents"
      ],
      "type": "string"
    },
    "job": {
      "definitions": {
        "artifact": {
          "description": "Artifacts are files created by a job build (e.g. JAR files)",
          "properties": {
            "location": {
              "description": "The relative path to find your artifact; it’s a path relative to the workspace directory; do not use absolute paths.",
              "type": "string"
            },
            "name": {
              "description": "Name of the artifact; in case artifact is shared, name must be unique within the plan.",
              "type": "string"
            },
            "pattern": {
              "description": "Name or Ant pattern of file(s) to keep.",
              "type": "string"
            },
            "required": {
              "type": "boolean"
            },
            "shared": {
              "default": false,
              "description": "You can share an artifact among other jobs or plans.",
              "type": "boolean"
            }
          },
          "title": "Artifact",
          "type": "object"
        },
        "task": {
          "description": "A task is a small unit of work, such as source code checkout, or running a script",
          "properties": {
            "checkout": {
              "properties": {
                "force-clean-build": {
                  "default": false,
                  "type": "string"
                },
                "path": {
                  "type": "string"
                },
                "repository": {
                  "type": "string"
                }
              },
              "type": "object"
            },
            "clean": {
              "type": "object"
            },
            "inject-variables": {
              "anyOf": [
                {
                  "type": "string"
                },
                {
                  "additionalProperties": false,
                  "properties": {
                    "file": {
                      "type": "string"
                    },
                    "namespace": {
                      "type": "string"
                    },
                    "scope": {
                      "type": "string"
                    }
                  },
                  "type": "object"
                }
              ]
            },
            "interpreter": {
              "type": "string"
            },
            "scripts": {
              "items": {
                "$ref": "#/definitions/script"
              },
              "minItems": 1,
              "type": "array"
            },
            "test-parser": {
              "anyOf": [
                {
                  "$ref": "#/definitions/testParser"
                },
                {
                  "properties": {
                    "ignore-time": {
                      "type": "boolean"
                    },
                    "test-results": {
                      "items": {
                        "type": "string"
                      },
                      "type": "array"
                    },
                    "type": {
                      "$ref": "#/definitions/testParser"
                    }
                  },
                  "required": ["type"],
                  "type": "object"
                }
              ],
              "description": "The Test Results Parser task in Bamboo parses test data"
            }
          },
          "type": "object"
        }
      },
      "description": "A job is a single build unit within a plan and is made up of one or more tasks.",
      "properties": {
        "docker": {
          "$ref": "#/definitions/docker"
        },
        "final-tasks": {
          "type": "array"
        },
        "key": {
          "type": "string"
        },
        "other": {
          "properties": {
            "clean-working-dir": {
              "type": "boolean"
            }
          },
          "type": "object"
        },
        "requirements": {
          "items": {
            "anyOf": [
              {
                "type": "string"
              },
              {
                "patternProperties": {
                  ".": {
                    "type": "string"
                  }
                },
                "type": "object"
              }
            ]
          },
          "type": "array"
        },
        "tasks": {
          "items": {
            "anyOf": [
              {
                "$ref": "#/definitions/predefinedTask"
              },
              {
                "$ref": "#/definitions/script"
              },
              {
                "$ref": "#/definitions/job/definitions/task"
              }
            ]
          },
          "type": "array"
        }
      },
      "title": "Job",
      "type": "object"
    },
    "keyValue": {
      "description": "Variables specific to a deployment environment",
      "patternProperties": {
        "[a-zA-Z0-9_]": {
          "anyOf": [
            {
              "type": "string"
            },
            {
              "type": "integer"
            },
            {
              "type": "boolean"
            },
            {
              "type": "number"
            }
          ]
        }
      },
      "type": "object"
    },
    "notification": {
      "properties": {
        "events": {
          "items": {
            "$ref": "#/definitions/events"
          },
          "minLength": 1,
          "type": "array"
        },
        "recipients": {
          "anyOf": [
            {
              "properties": {
                "users": {
                  "items": {
                    "type": "string"
                  },
                  "type": "array"
                }
              },
              "type": "object"
            },
            {
              "properties": {
                "groups": {
                  "items": {
                    "type": "string"
                  },
                  "type": "array"
                }
              },
              "type": "object"
            }
          ],
          "type": "array"
        }
      },
      "type": "object"
    },
    "permission": {
      "definitions": {
        "permission": {
          "description": "Plan permissions allow a user to control access to the functions of the build plan",
          "enum": ["view", "edit", "build", "admin", "clone", "deploy"],
          "type": "string"
        }
      },
      "description": "Plan permissions allow a user to control access to the functions of the build plan.",
      "properties": {
        "groups": {
          "anyOf": [
            {
              "type": "string"
            },
            {
              "items": {
                "type": "string"
              },
              "type": "array"
            }
          ]
        },
        "permissions": {
          "anyOf": [
            {
              "items": {
                "$ref": "#/definitions/permission/definitions/permission"
              },
              "type": "array"
            },
            {
              "$ref": "#/definitions/permission/definitions/permission"
            }
          ]
        },
        "roles": {
          "items": {
            "type": "string"
          },
          "type": "array"
        },
        "users": {
          "items": {
            "type": "string"
          },
          "type": "array"
        }
      },
      "type": "object"
    },
    "plan": {
      "description": "A plan defines everything about your continuous integration build process in Bamboo.",
      "properties": {
        "key": {
          "type": "string"
        },
        "name": {
          "type": "string"
        },
        "project-key": {
          "type": "string"
        }
      },
      "type": "object"
    },
    "predefinedTask": {
      "enum": ["inject-variables", "clean", "checkout", "artifact-download"],
      "type": "string"
    },
    "releaseNaming": {
      "properties": {
        "applies-to-branches": {
          "type": "boolean"
        },
        "auto-increment": {
          "type": "boolean"
        },
        "auto-increment-variables": {
          "anyOf": [
            {
              "type": "string"
            },
            {
              "items": {
                "type": "string"
              },
              "type": "array"
            }
          ]
        },
        "next-version-name": {
          "type": "string"
        }
      },
      "type": "object"
    },
    "script": {
      "anyOf": [
        {
          "type": "string"
        },
        {
          "properties": {
            "script": {
              "type": "string"
            }
          },
          "type": "object"
        }
      ]
    },
    "stage": {
      "additionalProperties": false,
      "description": "Stages group jobs to individual steps within a plan’s build process.",
      "properties": {
        "final": {
          "description": "Will be executed regardless of other stages state (pass or fail)",
          "type": "boolean"
        },
        "jobs": {
          "items": {
            "type": "string"
          },
          "type": "array"
        },
        "manual": {
          "description": "Will await for execution by user",
          "type": "boolean"
        }
      },
      "title": "Stage",
      "type": "object"
    },
    "task": {
      "definitions": {
        "trigger": {
          "anyOf": [
            {
              "properties": {
                "branch": {
                  "type": "string"
                },
                "stage": {
                  "type": "string"
                }
              },
              "type": "object"
            },
            {
              "patternProperties": {
                "[a-zA-Z0-9\\s+_-]": {
                  "type": "string"
                }
              },
              "type": "object"
            }
          ]
        }
      },
      "description": "A task is a small unit of work, such as source code checkout, or running a script.",
      "properties": {
        "artifacts": {
          "items": {
            "$ref": "#/definitions/job/definitions/artifact"
          },
          "type": "array"
        },
        "notifications": {
          "items": {
            "$ref": "#/definitions/notification"
          },
          "type": "array"
        },
        "source-plan": {
          "type": "string"
        },
        "triggers": {
          "items": {
            "patternProperties": {
              "(build|stage|environment)-success": {
                "$ref": "#/definitions/task/definitions/trigger"
              }
            },
            "type": "object"
          },
          "type": "array"
        }
      },
      "type": "object"
    },
    "testParser": {
      "enum": ["junit", "mstest", "nunit", "mocha", "testng"],
      "type": "string"
    },
    "triggers": {
      "definitions": {
        "cron": {
          "description": "Execute deployment by schedule.",
          "oneOf": [
            {
              "type": "string"
            },
            {
              "properties": {
                "expression": {
                  "type": "string"
                }
              },
              "type": "object"
            }
          ]
        },
        "polling": {
          "anyOf": [
            {
              "type": "integer"
            },
            {
              "properties": {
                "period": {
                  "type": "integer"
                }
              },
              "type": "object"
            }
          ]
        },
        "remote": {
          "anyOf": [
            {
              "const": "remote"
            },
            {
              "properties": {
                "remote": {
                  "type": "string"
                }
              },
              "type": "object"
            },
            {
              "properties": {
                "remote": {
                  "properties": {
                    "ip": {
                      "type": "string"
                    }
                  },
                  "type": "object"
                }
              },
              "type": "object"
            }
          ]
        }
      },
      "items": {
        "anyOf": [
          {
            "$ref": "#/definitions/triggers/definitions/polling"
          },
          {
            "$ref": "#/definitions/triggers/definitions/cron"
          },
          {
            "$ref": "#/definitions/triggers/definitions/remote"
          }
        ]
      },
      "type": "array"
    }
  },
  "description": "Full spec reference: https://docs.atlassian.com/bamboo-specs-docs/7.2.4/specs.html",
  "properties": {
    "default-environment-permissions": {
      "description": "These permissions apply to all environments defined in this deployment project",
      "items": {
        "$ref": "#/definitions/permission"
      },
      "title": "Default Environment Permissions",
      "type": "array"
    },
    "deployment": {
      "anyOf": [
        {
          "type": "string"
        },
        {
          "$ref": "#/definitions/deployment"
        }
      ],
      "title": "Deployment"
    },
    "deployment-permissions": {
      "description": "These permissions apply to the deployment project",
      "items": {
        "$ref": "#/definitions/permission"
      },
      "title": "Deployment Permissions",
      "type": "array"
    },
    "docker": {
      "$ref": "#/definitions/docker"
    },
    "environment-permissions": {
      "description": "Permissions specific to an environment",
      "items": {
        "patternProperties": {
          "[a-zA-Z0-9\\s+_-]": {
            "items": {
              "$ref": "#/definitions/permission"
            },
            "type": "array"
          }
        },
        "type": "object"
      },
      "title": "Environment Permissions",
      "type": "array"
    },
    "environments": {
      "description": "An environment represents the servers or groups of servers where the software release has been deployed to, and the tasks that are needed for the deployment to work smoothly",
      "items": {
        "type": "string"
      },
      "type": "array"
    },
    "labels": {
      "type": "string"
    },
    "notifications": {
      "items": {
        "properties": {
          "events": {
            "items": {
              "anyOf": [
                {
                  "$ref": "#/definitions/events"
                },
                {
                  "type": "object"
                }
              ]
            },
            "type": "array"
          },
          "recipients": {
            "items": {
              "anyOf": [
                {
                  "type": "string"
                },
                {
                  "properties": {
                    "emails": {
                      "items": {
                        "type": "string"
                      },
                      "type": "array"
                    },
                    "users": {
                      "items": {
                        "type": "string"
                      },
                      "type": "array"
                    }
                  },
                  "type": "object"
                }
              ]
            },
            "type": "array"
          }
        },
        "type": "object"
      },
      "type": "array"
    },
    "plan": {
      "$ref": "#/definitions/plan"
    },
    "plan-permissions": {
      "items": {
        "$ref": "#/definitions/permission"
      },
      "title": "Plan Permissions",
      "type": "array"
    },
    "release-naming": {
      "anyOf": [
        {
          "$ref": "#/definitions/releaseNaming"
        },
        {
          "type": "string"
        }
      ],
      "description": "You can define how releases should be named when they are created by Bamboo"
    },
    "stages": {
      "items": {
        "patternProperties": {
          "[a-zA-Z0-9\\s+_-]": {
            "anyOf": [
              {
                "items": {
                  "type": "string"
                },
                "type": "array"
              },
              {
                "$ref": "#/definitions/stage"
              }
            ]
          }
        },
        "type": "object"
      },
      "type": "array"
    },
    "triggers": {
      "$ref": "#/definitions/triggers"
    },
    "variables": {
      "$ref": "#/definitions/keyValue"
    },
    "version": {
      "default": 2,
      "type": "integer"
    }
  },
  "title": "Bamboo CI Specification",
  "type": "object"
}
